pipeline/__init__.py
pipeline/pipeline.py
pipeline-0.1.0.dist-info/METADATA
pipeline-0.1.0.dist-info/WHEEL
pipeline-0.1.0.dist-info/top_level.txt
pipeline-0.1.0.dist-info/RECORD
