Metadata-Version: 2.1
Name: pipeline
Version: 0.1.0
Summary: Command pipelines for Python.
Home-page: https://github.com/pooryorick/pipeline
Author: Poor Yorick
Author-email: org.pypi@pooryorick.com
License: UNKNOWN
Platform: UNKNOWN
Classifier: Programming Language :: Python :: 3
Classifier: License :: OSI Approved :: GNU General Public License v3 (GPLv3)
Classifier: Operating System :: OS Independent
Requires-Python: >=3.6
